borg.localrole-4.0.1-py3.13-nspkg.pth
borg/localrole/README.txt
borg/localrole/__init__.py
borg/localrole/config.py
borg/localrole/configure.zcml
borg/localrole/default.zcml
borg/localrole/default_adapter.py
borg/localrole/exportimport.zcml
borg/localrole/factory_adapter.py
borg/localrole/interfaces.py
borg/localrole/setuphandlers.py
borg/localrole/tests.py
borg/localrole/utils.py
borg/localrole/workspace.py
borg/localrole/bbb/__init__.py
borg/localrole/bbb/interfaces.py
borg/localrole/profiles/default/borg.localrole_various.txt
borg/localrole/profiles/default/import_steps.xml
borg/localrole/zmi/WorkspaceLocalRoleManagerForm.pt
borg_localrole-4.0.1.dist-info/METADATA
borg_localrole-4.0.1.dist-info/WHEEL
borg_localrole-4.0.1.dist-info/namespace_packages.txt
borg_localrole-4.0.1.dist-info/top_level.txt
borg_localrole-4.0.1.dist-info/RECORD
