Metadata-Version: 2.4
Name: borg.localrole
Version: 4.0.1
Summary: A PAS plugin which can manage local roles via an adapter lookup on the current context
Home-page: https://pypi.org/project/borg.localrole
Author: Borg Collective
Author-email: borg@plone.org
License: LGPL
Keywords: Plone PAS local roles
Platform: Any
Classifier: Development Status :: 5 - Production/Stable
Classifier: Environment :: Web Environment
Classifier: Framework :: Plone
Classifier: Framework :: Plone :: 5.0
Classifier: Framework :: Plone :: 5.1
Classifier: Framework :: Plone :: 5.2
Classifier: Framework :: Plone :: Core
Classifier: Intended Audience :: Other Audience
Classifier: Intended Audience :: System Administrators
Classifier: License :: OSI Approved :: GNU Library or Lesser General Public License (LGPL)
Classifier: Operating System :: OS Independent
Classifier: Programming Language :: Python
Classifier: Programming Language :: Python :: 3.8
Classifier: Programming Language :: Python :: 3.9
Classifier: Programming Language :: Python :: 3.10
Classifier: Programming Language :: Python :: 3.11
Classifier: Topic :: Software Development :: Libraries :: Python Modules
Requires-Python: >=3.8
Requires-Dist: AccessControl
Requires-Dist: setuptools
Requires-Dist: zope.annotation
Requires-Dist: zope.component
Requires-Dist: zope.deferredimport
Requires-Dist: zope.interface
Requires-Dist: Products.CMFCore
Requires-Dist: Products.GenericSetup
Requires-Dist: Products.PlonePAS>=5.0.1
Requires-Dist: Products.PluggableAuthService
Requires-Dist: plone.memoize
Requires-Dist: Acquisition
Requires-Dist: Zope
Provides-Extra: test
Requires-Dist: plone.app.testing; extra == "test"
Requires-Dist: plone.testing; extra == "test"
Dynamic: author
Dynamic: author-email
Dynamic: classifier
Dynamic: description
Dynamic: description-content-type
Dynamic: home-page
Dynamic: keywords
Dynamic: license
Dynamic: platform
Dynamic: provides-extra
Dynamic: requires-dist
Dynamic: requires-python
Dynamic: summary
